Metadata-Version: 1.1
Name: riboSeed
Version: 0.4.87
Summary: riboSeed: assemble across rDNA regions
Home-page: https://github.com/nickp60/riboSeed
Author: Nick Waters
Author-email: nickp60@gmail.com
License: MIT
Keywords: bioinformatics assembly genomics development
Platform: UNKNOWN
Classifier: Development Status :: 3 - Alpha
Classifier: Intended Audience :: Developers
Classifier: Intended Audience :: Science/Research
Classifier: Topic :: Scientific/Engineering :: Bio-Informatics
Classifier: License :: OSI Approved :: MIT License
Classifier: Programming Language :: Python :: 3.5
Classifier: Programming Language :: Python :: 3.6
